{
  "date": "2026-01-13",
  "start_time": "2026-01-13T08:00:05.022722",
  "status": "SUCCESS",
  "market_status": {
    "is_open": true,
    "status": "OPEN",
    "message": "Market is OPEN",
    "current_time_et": "11:00 AM ET",
    "current_date": "Tuesday, January 13, 2026"
  },
  "regime_analysis": {
    "regime": "NEUTRAL",
    "confidence": "MEDIUM",
    "spy_price": 693.7138061523438,
    "spy_change_pct": -0.2080336969986657,
    "vix_level": 15.6899995803833,
    "recommendation": "NORMAL CONDITIONS"
  },
  "plan_generated": true,
  "plan_approved": true,
  "trades_executed": [
    {
      "ticker": "IPG",
      "action": "SELL",
      "status": "SKIPPED",
      "reason": "Asset not tradeable: AssetStatus.INACTIVE"
    }
  ],
  "portfolio_state": {
    "timestamp": "2026-01-13T08:08:01.936593",
    "equity": 101804.14,
    "cash": 77178.76,
    "buying_power": 175272.83,
    "portfolio_value": 101804.14,
    "starting_capital": 100000.0,
    "total_return": 1804.1399999999994,
    "total_return_pct": 1.8041399999999996,
    "daily_pl": 3743.6399999999994,
    "daily_pl_pct": 3.817683980807766,
    "total_unrealized_pl": 758.5099999999999,
    "position_count": 3,
    "positions": [
      {
        "ticker": "ESI",
        "shares": 372.0,
        "entry_price": 26.94,
        "current_price": 28.42,
        "market_value": 10572.24,
        "unrealized_pl": 550.56,
        "unrealized_pl_pct": 5.49368968077209
      },
      {
        "ticker": "F",
        "shares": 738.0,
        "entry_price": 13.59,
        "current_price": 14.015,
        "market_value": 10343.07,
        "unrealized_pl": 313.65,
        "unrealized_pl_pct": 3.12729948491538
      },
      {
        "ticker": "IPG",
        "shares": 151.0,
        "entry_price": 25.27,
        "current_price": 24.57,
        "market_value": 3710.07,
        "unrealized_pl": -105.7,
        "unrealized_pl_pct": -2.7700831024930697
      }
    ]
  },
  "warnings": [],
  "errors": [],
  "position_drift": {
    "positions_checked": 3,
    "oversized_count": 0,
    "trim_recommendations": 0
  },
  "plan_summary": {
    "plan_id": "PLAN_20260113_080745",
    "total_trades": 1,
    "quality_score": 76,
    "ceo_rating": "GOOD",
    "ceo_recommendation": "RECOMMEND APPROVAL"
  },
  "sells_count": 0,
  "buys_count": 0,
  "verification": {
    "passed": true,
    "issues": [],
    "summary": {
      "position_count": 3,
      "sells_executed": 0,
      "buys_executed": 0,
      "expected_count_change": 0
    }
  },
  "fill_sync": {
    "orders_checked": 0,
    "fills_recorded": 0,
    "orders_updated": 0,
    "already_recorded": 0,
    "no_match_in_db": 0,
    "errors": []
  },
  "end_time": "2026-01-13T08:08:03.507002",
  "duration_seconds": 478.484294
}